sona/__init__.py
sona/__main__.py
sona/core/commands.py
sona/core/exceptions.py
sona/core/inferencer.py
sona/core/messages/__init__.py
sona/core/messages/base.py
sona/core/messages/context.py
sona/core/messages/file.py
sona/core/messages/job.py
sona/core/messages/result.py
sona/core/messages/state.py
sona/core/middlewares/__init__.py
sona/core/middlewares/base.py
sona/core/storages/__init__.py
sona/core/storages/azureblob.py
sona/core/storages/base.py
sona/core/storages/filters/audio.py
sona/core/storages/local.py
sona/core/storages/s3.py
sona/core/storages/sources/__init__.py
sona/core/storages/sources/azureblob.py
sona/core/storages/sources/base.py
sona/core/storages/sources/gdrive.py
sona/core/storages/sources/http.py
sona/core/storages/sources/local.py
sona/core/storages/sources/s3.py
sona/core/storages/sources/youtube.py
sona/core/stream/inferencer.py
sona/core/stream/messages/__init__.py
sona/core/stream/messages/context.py
sona/core/stream/messages/streamdata.py
sona/core/stream/parsers/audio.py
sona/settings.py
sona/utils/common.py
sona_core-2.0.0.dist-info/LICENSE
sona_core-2.0.0.dist-info/METADATA
sona_core-2.0.0.dist-info/WHEEL
sona_core-2.0.0.dist-info/entry_points.txt
sona_core-2.0.0.dist-info/RECORD
