Metadata-Version: 2.1
Name: sona-core
Version: 2.0.0
Summary: 
Author: dwave-dev
Requires-Python: >=3.8,<4.0
Classifier: Programming Language :: Python :: 3
Classifier: Programming Language :: Python :: 3.8
Classifier: Programming Language :: Python :: 3.9
Classifier: Programming Language :: Python :: 3.10
Classifier: Programming Language :: Python :: 3.11
Classifier: Programming Language :: Python :: 3.12
Requires-Dist: av
Requires-Dist: azure-identity (>=1.15.0,<2.0.0)
Requires-Dist: azure-storage-blob (>=12.19.0,<13.0.0)
Requires-Dist: boto3 (>=1.34.14,<2.0.0)
Requires-Dist: loguru (>=0.7.2,<0.8.0)
Requires-Dist: pydantic-settings (>=2.2.1,<3.0.0)
Requires-Dist: typer (>=0.9.0,<0.10.0)
Requires-Dist: wget (>=3.2,<4.0)
Requires-Dist: yt-dlp
